ucapi/__init__.py
ucapi/_version.py
ucapi/api.py
ucapi/api_definitions.py
ucapi/button.py
ucapi/climate.py
ucapi/cover.py
ucapi/entities.py
ucapi/entity.py
ucapi/ir_emitter.py
ucapi/light.py
ucapi/media_player.py
ucapi/remote.py
ucapi/select.py
ucapi/sensor.py
ucapi/switch.py
ucapi/ui.py
ucapi/voice_assistant.py
ucapi/voice_stream.py
ucapi/proto/__init__.py
ucapi/proto/ucr_integration_voice.proto
ucapi/proto/ucr_integration_voice_pb2.py
ucapi/proto/ucr_integration_voice_pb2.pyi
ucapi-0.5.2.dist-info/licenses/LICENSE
ucapi-0.5.2.dist-info/METADATA
ucapi-0.5.2.dist-info/WHEEL
ucapi-0.5.2.dist-info/top_level.txt
ucapi-0.5.2.dist-info/RECORD
