Metadata-Version: 2.4
Name: ucapi
Version: 0.5.2
Summary: Python wrapper for the Unfolded Circle Integration API
Author-email: Unfolded Circle ApS <hello@unfoldedcircle.com>
License: MPL-2.0
Project-URL: Homepage, https://www.unfoldedcircle.com/
Project-URL: Source Code, https://github.com/unfoldedcircle/integration-python-library
Project-URL: Bug Reports, https://github.com/unfoldedcircle/integration-python-library/issues
Project-URL: Discord, http://unfolded.chat/
Project-URL: Forum, https://unfolded.community/
Platform: any
Classifier: Development Status :: 4 - Beta
Classifier: Intended Audience :: Developers
Classifier: License :: OSI Approved :: Mozilla Public License 2.0 (MPL 2.0)
Classifier: Operating System :: OS Independent
Classifier: Topic :: Software Development :: Libraries
Classifier: Topic :: Home Automation
Classifier: Programming Language :: Python :: 3.11
Requires-Python: >=3.11
License-File: LICENSE
Requires-Dist: protobuf~=6.33.2
Requires-Dist: pyee>=9.0
Requires-Dist: websockets>=14.0
Requires-Dist: zeroconf>=0.120.0
Provides-Extra: testing
Requires-Dist: pylint==4.0.4; extra == "testing"
Requires-Dist: flake8-docstrings; extra == "testing"
Requires-Dist: flake8; extra == "testing"
Requires-Dist: black; extra == "testing"
Requires-Dist: isort; extra == "testing"
Dynamic: license-file
